LICENSE
README.md
setup.py
eqcct/__init__.py
eqcct/plot.py
eqcct/stream.py
eqcct/utils.py
eqcct.egg-info/PKG-INFO
eqcct.egg-info/SOURCES.txt
eqcct.egg-info/dependency_links.txt
eqcct.egg-info/not-zip-safe
eqcct.egg-info/requires.txt
eqcct.egg-info/top_level.txt